{
  "project_info": {
    "project_number": "632955617876",
    "project_id": "agendapediatrica"
  },
  "client": [
    {
      "client_info": {
        "mobilesdk_app_id": "1:632955617876:android:a652ff838fede3b4",
        "android_client_info": {
          "package_name": "com.agendaapp.agendapediatrica"
        }
      },
      "oauth_client": [
        {
          "client_id": "632955617876-dfgn0544tj8dp8h4fris36hiuv85tu99.apps.googleusercontent.com",
          "client_type": 3
        },
        {
          "client_id": "632955617876-d246bj1tjn7b8mcp6s5tju9m5mkvj2e5.apps.googleusercontent.com",
          "client_type": 1,
          "android_info": {
            "package_name": "com.agendaapp.agendapediatrica",
            "certificate_hash": "4113fcaf0b8a30c6a83685d81247a2dd95814760"
          }
        }
      ],
      "api_key": [
        {
          "current_key": "AIzaSyDUK7nR-6oek-6xBKmYmQz4QoWON08rJCU"
        }
      ],
      "services": {
        "analytics_service": {
          "status": 1
        },
        "appinvite_service": {
          "status": 1,
          "other_platform_oauth_client": []
        },
        "ads_service": {
          "status": 1
        }
      }
    }
  ],
  "configuration_version": "1"
}